secure_password_generator_ikac/__init__.py
secure_password_generator_ikac/foo.py
secure_password_generator_ikac-0.0.2.dist-info/LICENSE
secure_password_generator_ikac-0.0.2.dist-info/METADATA
secure_password_generator_ikac-0.0.2.dist-info/WHEEL
secure_password_generator_ikac-0.0.2.dist-info/RECORD
