Metadata-Version: 2.1
Name: secure_password_generator_ikac
Version: 0.0.2
Summary: Un proyecto en Python que genera contraseñas fuertes y seguras para mejorar la seguridad en línea.
Home-page: https://github.com/Ingrid1802/secure-password-generator-ikac
Author: Ingrid
Author-email: ingridaybar841@gmail.com
Requires-Python: >=3.8,<4.0
Classifier: Programming Language :: Python :: 3
Classifier: Programming Language :: Python :: 3.8
Classifier: Programming Language :: Python :: 3.9
Classifier: Programming Language :: Python :: 3.10
Classifier: Programming Language :: Python :: 3.11
Classifier: Programming Language :: Python :: 3.12
Project-URL: Documentation, https://Ingrid1802.github.io/secure-password-generator-ikac/
Project-URL: Repository, https://github.com/Ingrid1802/secure-password-generator-ikac
